bert_clf/__init__.py
bert_clf/pipeline.py
bert_clf/utils.py
bert_clf/src/__init__.py
bert_clf/src/dataset.py
bert_clf/src/early_stopping.py
bert_clf/src/preparing_data_utils.py
bert_clf/src/training_utils.py
bert_clf/src/core/BaseDataset.py
bert_clf/src/core/BaseModel.py
bert_clf/src/core/Fabric.py
bert_clf/src/core/__init__.py
bert_clf/src/core/utils.py
bert_clf/src/models/BertCLF.py
bert_clf/src/models/EncoderCLF.py
bert_clf/src/models/__init__.py
bert_clf/src/pandas_dataset/PandasDataset.py
bert_clf/src/pandas_dataset/SimpleDataFrame.py
bert_clf/src/pandas_dataset/__init__.py
bert_for_sequence_classification-0.1.1.dist-info/LICENSE
bert_for_sequence_classification-0.1.1.dist-info/METADATA
bert_for_sequence_classification-0.1.1.dist-info/WHEEL
bert_for_sequence_classification-0.1.1.dist-info/entry_points.txt
bert_for_sequence_classification-0.1.1.dist-info/top_level.txt
bert_for_sequence_classification-0.1.1.dist-info/RECORD
