Metadata-Version: 2.1
Name: bert-for-sequence-classification
Version: 0.1.1
Summary: Easy fine-tuning for BERT models
Author: Tatiana Iazykova
Author-email: tania_yazykova@bk.ru
Keywords: python,bert,deep learning,nlp
Classifier: Development Status :: 3 - Alpha
Classifier: Programming Language :: Python :: 3.7
Classifier: Programming Language :: Python :: 3.8
Classifier: Programming Language :: Python :: 3.9
License-File: LICENSE
Requires-Dist: transformers (>=4.21.0)
Requires-Dist: torch (>=1.7.1)
Requires-Dist: numpy (>=1.19.5)
Requires-Dist: pandas (>=1.1.5)
Requires-Dist: scikit-learn (>=1.0)
Requires-Dist: pyyaml (>=6.0)
Requires-Dist: openpyxl (>=3.0.9)
Requires-Dist: wget
Requires-Dist: tqdm
